<annotation>
	<folder>train</folder>
	<filename>images - 2019-09-24T172831.489.jpg</filename>
	<path>D:\tensorflow\models\research\object_detection\images\train\images - 2019-09-24T172831.489.jpg</path>
	<source>
		<database>Unknown</database>
	</source>
	<size>
		<width>274</width>
		<height>184</height>
		<depth>3</depth>
	</size>
	<segmented>0</segmented>
	<object>
		<name>bonnet</name>
		<pose>Unspecified</pose>
		<truncated>0</truncated>
		<difficult>0</difficult>
		<bndbox>
			<xmin>96</xmin>
			<ymin>25</ymin>
			<xmax>231</xmax>
			<ymax>85</ymax>
		</bndbox>
	</object>
	<object>
		<name>bumper</name>
		<pose>Unspecified</pose>
		<truncated>0</truncated>
		<difficult>0</difficult>
		<bndbox>
			<xmin>76</xmin>
			<ymin>98</ymin>
			<xmax>159</xmax>
			<ymax>160</ymax>
		</bndbox>
	</object>
</annotation>
